lazily_sliced.py
lazily_sliced-0.1.0a0.dist-info/METADATA
lazily_sliced-0.1.0a0.dist-info/WHEEL
lazily_sliced-0.1.0a0.dist-info/top_level.txt
lazily_sliced-0.1.0a0.dist-info/RECORD
