Metadata-Version: 2.4
Name: lazily-sliced
Version: 0.1.0a0
Summary: A memory-efficient Python sequence wrapper that applies slicing operations lazily, deferring data access until elements are actually needed.
Author-email: Jifeng Wu <jifengwu2k@gmail.com>
License-Expression: MIT
Project-URL: Homepage, https://github.com/jifengwu2k/lazily-sliced
Project-URL: Bug Tracker, https://github.com/jifengwu2k/lazily-sliced/issues
Classifier: Programming Language :: Python :: 2
Classifier: Programming Language :: Python :: 3
Classifier: Operating System :: OS Independent
Requires-Python: >=2
